Workbook

Sheet Population_Data
M2: Population Data
B6: Gender | C6: Column1 | D6: Age | E6: Field Of Work | F6: Column2 | G6: Education | H6: Kids | I6: Cars | J6: Column3 | K6: Area | L6: Income | M6: Value Of House | N6: Mortgage Left | O6: Car Value | P6: Car Payment Left | Q6: Debts | R6: Investments | S6: Total Assets | T6: Total Liabilities | U6: Net Worth | Y6: Field Of Work | AB6: Education | AE6: Area
A7: =RANDBETWEEN(1,2) -> 1 | B7: =IF(A7=1,"M","F") -> M | C7: =RANDBETWEEN(1,7) -> 7 | D7: =RANDBETWEEN(18,45) -> 40 | E7: =VLOOKUP(C7,$Y$7:$Z$13,2) -> Other | F7: =RANDBETWEEN(1,7) -> 4 | G7: =VLOOKUP(F7,$AB$7:$AC$13,2) -> PG | H7: =RANDBETWEEN(0,4) -> 3 | I7: =RANDBETWEEN(0,3) -> 1 | J7: =RANDBETWEEN(1,28) -> 20 | K7: =VLOOKUP(J7,$AE$7:$AF$34,2) -> Nagaland | L7: =RANDBETWEEN(25000,99000) -> 37019 | M7: =L7*RANDBETWEEN(5,9) -> 296152 | N7: =RAND()*M7 -> 286301.49 | O7: =RAND()*I7*L7 -> 26911.522 | P7: =O7*RAND() -> 12304.765 | Q7: =RAND()*L7 -> 213.46194 | R7: =RAND()*L7 -> 7004.4438 | S7: =M7+O7+R7 -> 330067.97 | T7: =N7+P7+Q7 -> 298819.71 | U7: =S7-T7 -> 31248.253 | Y7: 1 | Z7: Engineering | AB7: 1 | AC7: Secondary | AE7: 1 | AF7: Haryana
A8: =RANDBETWEEN(1,2) -> 2 | B8: =IF(A8=1,"M","F") -> F | C8: =RANDBETWEEN(1,7) -> 6 | D8: =RANDBETWEEN(18,45) -> 38 | E8: =VLOOKUP(C8,$Y$7:$Z$13,2) -> Art | F8: =RANDBETWEEN(1,7) -> 4 | G8: =VLOOKUP(F8,$AB$7:$AC$13,2) -> PG | H8: =RANDBETWEEN(0,4) -> 4 | I8: =RANDBETWEEN(0,3) -> 1 | J8: =RANDBETWEEN(1,28) -> 7 | K8: =VLOOKUP(J8,$AE$7:$AF$34,2) -> Assam | L8: =RANDBETWEEN(25000,99000) -> 61650 | M8: =L8*RANDBETWEEN(5,9) -> 554850 | N8: =RAND()*M8 -> 478311.92 | O8: =RAND()*I8*L8 -> 32069.756 | P8: =O8*RAND() -> 28643.236 | Q8: =RAND()*L8 -> 24145.096 | R8: =RAND()*L8 -> 23801.704 | S8: =M8+O8+R8 -> 610721.46 | T8: =N8+P8+Q8 -> 531100.25 | U8: =S8-T8 -> 79621.208 | Y8: 2 | Z8: Healthcare | AB8: 2 | AC8: Senior Secondary | AE8: 2 | AF8: Uttar Pradesh
A9: =RANDBETWEEN(1,2) -> 2 | B9: =IF(A9=1,"M","F") -> F | C9: =RANDBETWEEN(1,7) -> 1 | D9: =RANDBETWEEN(18,45) -> 25 | E9: =VLOOKUP(C9,$Y$7:$Z$13,2) -> Engineering | F9: =RANDBETWEEN(1,7) -> 6 | G9: =VLOOKUP(F9,$AB$7:$AC$13,2) -> Doctorate | H9: =RANDBETWEEN(0,4) -> 0 | I9: =RANDBETWEEN(0,3) -> 0 | J9: =RANDBETWEEN(1,28) -> 25 | K9: =VLOOKUP(J9,$AE$7:$AF$34,2) -> Telangana | L9: =RANDBETWEEN(25000,99000) -> 84621 | M9: =L9*RANDBETWEEN(5,9) -> 507726 | N9: =RAND()*M9 -> 226283.11 | O9: =RAND()*I9*L9 -> 0 | P9: =O9*RAND() -> 0 | Q9: =RAND()*L9 -> 57143.754 | R9: =RAND()*L9 -> 25161.764 | S9: =M9+O9+R9 -> 532887.76 | T9: =N9+P9+Q9 -> 283426.87 | U9: =S9-T9 -> 249460.9 | Y9: 3 | Z9: IT | AB9: 3 | AC9: UG | AE9: 3 | AF9: Punjab
A10: =RANDBETWEEN(1,2) -> 2 | B10: =IF(A10=1,"M","F") -> F | C10: =RANDBETWEEN(1,7) -> 7 | D10: =RANDBETWEEN(18,45) -> 21 | E10: =VLOOKUP(C10,$Y$7:$Z$13,2) -> Other | F10: =RANDBETWEEN(1,7) -> 7 | G10: =VLOOKUP(F10,$AB$7:$AC$13,2) -> Other | H10: =RANDBETWEEN(0,4) -> 3 | I10: =RANDBETWEEN(0,3) -> 3 | J10: =RANDBETWEEN(1,28) -> 5 | K10: =VLOOKUP(J10,$AE$7:$AF$34,2) -> Andhra Pradesh | L10: =RANDBETWEEN(25000,99000) -> 28542 | M10: =L10*RANDBETWEEN(5,9) -> 256878 | N10: =RAND()*M10 -> 180844.5 | O10: =RAND()*I10*L10 -> 66923.497 | P10: =O10*RAND() -> 19635.757 | Q10: =RAND()*L10 -> 15127.081 | R10: =RAND()*L10 -> 8420.8862 | S10: =M10+O10+R10 -> 332222.38 | T10: =N10+P10+Q10 -> 215607.34 | U10: =S10-T10 -> 116615.04 | Y10: 4 | Z10: Accounting | AB10: 4 | AC10: PG | AE10: 4 | AF10: Maharashtra
A11: =RANDBETWEEN(1,2) -> 1 | B11: =IF(A11=1,"M","F") -> M | C11: =RANDBETWEEN(1,7) -> 7 | D11: =RANDBETWEEN(18,45) -> 21 | E11: =VLOOKUP(C11,$Y$7:$Z$13,2) -> Other | F11: =RANDBETWEEN(1,7) -> 2 | G11: =VLOOKUP(F11,$AB$7:$AC$13,2) -> Senior Secondary | H11: =RANDBETWEEN(0,4) -> 4 | I11: =RANDBETWEEN(0,3) -> 1 | J11: =RANDBETWEEN(1,28) -> 21 | K11: =VLOOKUP(J11,$AE$7:$AF$34,2) -> Odisha | L11: =RANDBETWEEN(25000,99000) -> 53641 | M11: =L11*RANDBETWEEN(5,9) -> 429128 | N11: =RAND()*M11 -> 264389.02 | O11: =RAND()*I11*L11 -> 5371.6184 | P11: =O11*RAND() -> 611.40943 | Q11: =RAND()*L11 -> 19134.351 | R11: =RAND()*L11 -> 21563.43 | S11: =M11+O11+R11 -> 456063.05 | T11: =N11+P11+Q11 -> 284134.78 | U11: =S11-T11 -> 171928.27 | Y11: 5 | Z11: Research | AB11: 5 | AC11: Diploma | AE11: 5 | AF11: Andhra Pradesh
A12: =RANDBETWEEN(1,2) -> 2 | B12: =IF(A12=1,"M","F") -> F | C12: =RANDBETWEEN(1,7) -> 6 | D12: =RANDBETWEEN(18,45) -> 35 | E12: =VLOOKUP(C12,$Y$7:$Z$13,2) -> Art | F12: =RANDBETWEEN(1,7) -> 3 | G12: =VLOOKUP(F12,$AB$7:$AC$13,2) -> UG | H12: =RANDBETWEEN(0,4) -> 2 | I12: =RANDBETWEEN(0,3) -> 2 | J12: =RANDBETWEEN(1,28) -> 22 | K12: =VLOOKUP(J12,$AE$7:$AF$34,2) -> Rajasthan | L12: =RANDBETWEEN(25000,99000) -> 49963 | M12: =L12*RANDBETWEEN(5,9) -> 399704 | N12: =RAND()*M12 -> 51301.645 | O12: =RAND()*I12*L12 -> 67299.365 | P12: =O12*RAND() -> 19265.575 | Q12: =RAND()*L12 -> 18926.675 | R12: =RAND()*L12 -> 2355.4636 | S12: =M12+O12+R12 -> 469358.83 | T12: =N12+P12+Q12 -> 89493.895 | U12: =S12-T12 -> 379864.93 | Y12: 6 | Z12: Art | AB12: 6 | AC12: Doctorate | AE12: 6 | AF12: Arunachal Pradesh
A13: =RANDBETWEEN(1,2) -> 2 | B13: =IF(A13=1,"M","F") -> F | C13: =RANDBETWEEN(1,7) -> 7 | D13: =RANDBETWEEN(18,45) -> 39 | E13: =VLOOKUP(C13,$Y$7:$Z$13,2) -> Other | F13: =RANDBETWEEN(1,7) -> 6 | G13: =VLOOKUP(F13,$AB$7:$AC$13,2) -> Doctorate | H13: =RANDBETWEEN(0,4) -> 2 | I13: =RANDBETWEEN(0,3) -> 1 | J13: =RANDBETWEEN(1,28) -> 18 | K13: =VLOOKUP(J13,$AE$7:$AF$34,2) -> Meghalya | L13: =RANDBETWEEN(25000,99000) -> 72404 | M13: =L13*RANDBETWEEN(5,9) -> 651636 | N13: =RAND()*M13 -> 548199.73 | O13: =RAND()*I13*L13 -> 48050.537 | P13: =O13*RAND() -> 38226.461 | Q13: =RAND()*L13 -> 61897.94 | R13: =RAND()*L13 -> 19022.126 | S13: =M13+O13+R13 -> 718708.66 | T13: =N13+P13+Q13 -> 648324.13 | U13: =S13-T13 -> 70384.532 | Y13: 7 | Z13: Other | AB13: 7 | AC13: Other | AE13: 7 | AF13: Assam
A14: =RANDBETWEEN(1,2) -> 1 | B14: =IF(A14=1,"M","F") -> M | C14: =RANDBETWEEN(1,7) -> 2 | D14: =RANDBETWEEN(18,45) -> 26 | E14: =VLOOKUP(C14,$Y$7:$Z$13,2) -> Healthcare | F14: =RANDBETWEEN(1,7) -> 1 | G14: =VLOOKUP(F14,$AB$7:$AC$13,2) -> Secondary | H14: =RANDBETWEEN(0,4) -> 3 | I14: =RANDBETWEEN(0,3) -> 0 | J14: =RANDBETWEEN(1,28) -> 22 | K14: =VLOOKUP(J14,$AE$7:$AF$34,2) -> Rajasthan | L14: =RANDBETWEEN(25000,99000) -> 76679 | M14: =L14*RANDBETWEEN(5,9) -> 690111 | N14: =RAND()*M14 -> 399871.77 | O14: =RAND()*I14*L14 -> 0 | P14: =O14*RAND() -> 0 | Q14: =RAND()*L14 -> 75702.724 | R14: =RAND()*L14 -> 19916.081 | S14: =M14+O14+R14 -> 710027.08 | T14: =N14+P14+Q14 -> 475574.49 | U14: =S14-T14 -> 234452.59 | AE14: 8 | AF14: Bihar
A15: =RANDBETWEEN(1,2) -> 2 | B15: =IF(A15=1,"M","F") -> F | C15: =RANDBETWEEN(1,7) -> 7 | D15: =RANDBETWEEN(18,45) -> 26 | E15: =VLOOKUP(C15,$Y$7:$Z$13,2) -> Other | F15: =RANDBETWEEN(1,7) -> 5 | G15: =VLOOKUP(F15,$AB$7:$AC$13,2) -> Diploma | H15: =RANDBETWEEN(0,4) -> 2 | I15: =RANDBETWEEN(0,3) -> 1 | J15: =RANDBETWEEN(1,28) -> 24 | K15: =VLOOKUP(J15,$AE$7:$AF$34,2) -> Tamil Nadu | L15: =RANDBETWEEN(25000,99000) -> 86423 | M15: =L15*RANDBETWEEN(5,9) -> 518538 | N15: =RAND()*M15 -> 355024.74 | O15: =RAND()*I15*L15 -> 80924.914 | P15: =O15*RAND() -> 68559.652 | Q15: =RAND()*L15 -> 66060.147 | R15: =RAND()*L15 -> 66457.486 | S15: =M15+O15+R15 -> 665920.4 | T15: =N15+P15+Q15 -> 489644.54 | U15: =S15-T15 -> 176275.86 | AE15: 9 | AF15: Chhattisgarh
A16: =RANDBETWEEN(1,2) -> 2 | B16: =IF(A16=1,"M","F") -> F | C16: =RANDBETWEEN(1,7) -> 4 | D16: =RANDBETWEEN(18,45) -> 36 | E16: =VLOOKUP(C16,$Y$7:$Z$13,2) -> Accounting | F16: =RANDBETWEEN(1,7) -> 5 | G16: =VLOOKUP(F16,$AB$7:$AC$13,2) -> Diploma | H16: =RANDBETWEEN(0,4) -> 0 | I16: =RANDBETWEEN(0,3) -> 3 | J16: =RANDBETWEEN(1,28) -> 2 | K16: =VLOOKUP(J16,$AE$7:$AF$34,2) -> Uttar Pradesh | L16: =RANDBETWEEN(25000,99000) -> 88851 | M16: =L16*RANDBETWEEN(5,9) -> 444255 | N16: =RAND()*M16 -> 285255.46 | O16: =RAND()*I16*L16 -> 98036.043 | P16: =O16*RAND() -> 78219.977 | Q16: =RAND()*L16 -> 378.18978 | R16: =RAND()*L16 -> 11582.395 | S16: =M16+O16+R16 -> 553873.44 | T16: =N16+P16+Q16 -> 363853.63 | U16: =S16-T16 -> 190019.81 | AE16: 10 | AF16: Gujarat
A17: =RANDBETWEEN(1,2) -> 2 | B17: =IF(A17=1,"M","F") -> F | C17: =RANDBETWEEN(1,7) -> 6 | D17: =RANDBETWEEN(18,45) -> 31 | E17: =VLOOKUP(C17,$Y$7:$Z$13,2) -> Art | F17: =RANDBETWEEN(1,7) -> 6 | G17: =VLOOKUP(F17,$AB$7:$AC$13,2) -> Doctorate | H17: =RANDBETWEEN(0,4) -> 3 | I17: =RANDBETWEEN(0,3) -> 0 | J17: =RANDBETWEEN(1,28) -> 6 | K17: =VLOOKUP(J17,$AE$7:$AF$34,2) -> Arunachal Pradesh | L17: =RANDBETWEEN(25000,99000) -> 69520 | M17: =L17*RANDBETWEEN(5,9) -> 417120 | N17: =RAND()*M17 -> 343405.29 | O17: =RAND()*I17*L17 -> 0 | P17: =O17*RAND() -> 0 | Q17: =RAND()*L17 -> 32864.522 | R17: =RAND()*L17 -> 42402.252 | S17: =M17+O17+R17 -> 459522.25 | T17: =N17+P17+Q17 -> 376269.81 | U17: =S17-T17 -> 83252.441 | AE17: 11 | AF17: Goa
A18: =RANDBETWEEN(1,2) -> 1 | B18: =IF(A18=1,"M","F") -> M | C18: =RANDBETWEEN(1,7) -> 4 | D18: =RANDBETWEEN(18,45) -> 22 | E18: =VLOOKUP(C18,$Y$7:$Z$13,2) -> Accounting | F18: =RANDBETWEEN(1,7) -> 1 | G18: =VLOOKUP(F18,$AB$7:$AC$13,2) -> Secondary | H18: =RANDBETWEEN(0,4) -> 0 | I18: =RANDBETWEEN(0,3) -> 1 | J18: =RANDBETWEEN(1,28) -> 26 | K18: =VLOOKUP(J18,$AE$7:$AF$34,2) -> Tripura | L18: =RANDBETWEEN(25000,99000) -> 82010 | M18: =L18*RANDBETWEEN(5,9) -> 656080 | N18: =RAND()*M18 -> 202168.23 | O18: =RAND()*I18*L18 -> 70184.446 | P18: =O18*RAND() -> 53447.106 | Q18: =RAND()*L18 -> 75877.263 | R18: =RAND()*L18 -> 72086.78 | S18: =M18+O18+R18 -> 798351.23 | T18: =N18+P18+Q18 -> 331492.6 | U18: =S18-T18 -> 466858.62 | AE18: 12 | AF18: Himachal Pradesh
A19: =RANDBETWEEN(1,2) -> 1 | B19: =IF(A19=1,"M","F") -> M | C19: =RANDBETWEEN(1,7) -> 7 | D19: =RANDBETWEEN(18,45) -> 44 | E19: =VLOOKUP(C19,$Y$7:$Z$13,2) -> Other | F19: =RANDBETWEEN(1,7) -> 3 | G19: =VLOOKUP(F19,$AB$7:$AC$13,2) -> UG | H19: =RANDBETWEEN(0,4) -> 4 | I19: =RANDBETWEEN(0,3) -> 3 | J19: =RANDBETWEEN(1,28) -> 4 | K19: =VLOOKUP(J19,$AE$7:$AF$34,2) -> Maharashtra | L19: =RANDBETWEEN(25000,99000) -> 30256 | M19: =L19*RANDBETWEEN(5,9) -> 151280 | N19: =RAND()*M19 -> 7281.9647 | O19: =RAND()*I19*L19 -> 13813.027 | P19: =O19*RAND() -> 9966.7686 | Q19: =RAND()*L19 -> 8363.1906 | R19: =RAND()*L19 -> 9071.824 | S19: =M19+O19+R19 -> 174164.85 | T19: =N19+P19+Q19 -> 25611.924 | U19: =S19-T19 -> 148552.93 | AE19: 13 | AF19: Jharkhand
A20: =RANDBETWEEN(1,2) -> 1 | B20: =IF(A20=1,"M","F") -> M | C20: =RANDBETWEEN(1,7) -> 4 | D20: =RANDBETWEEN(18,45) -> 40 | E20: =VLOOKUP(C20,$Y$7:$Z$13,2) -> Accounting | F20: =RANDBETWEEN(1,7) -> 6 | G20: =VLOOKUP(F20,$AB$7:$AC$13,2) -> Doctorate | H20: =RANDBETWEEN(0,4) -> 2 | I20: =RANDBETWEEN(0,3) -> 2 | J20: =RANDBETWEEN(1,28) -> 20 | K20: =VLOOKUP(J20,$AE$7:$AF$34,2) -> Nagaland | L20: =RANDBETWEEN(25000,99000) -> 77033 | M20: =L20*RANDBETWEEN(5,9) -> 693297 | N20: =RAND()*M20 -> 51354.067 | O20: =RAND()*I20*L20 -> 26253.439 | P20: =O20*RAND() -> 22284.473 | Q20: =RAND()*L20 -> 24100.768 | R20: =RAND()*L20 -> 16640.708 | S20: =M20+O20+R20 -> 736191.15 | T20: =N20+P20+Q20 -> 97739.308 | U20: =S20-T20 -> 638451.84 | AE20: 14 | AF20: Karnataka
A21: =RANDBETWEEN(1,2) -> 1 | B21: =IF(A21=1,"M","F") -> M | C21: =RANDBETWEEN(1,7) -> 5 | D21: =RANDBETWEEN(18,45) -> 32 | E21: =VLOOKUP(C21,$Y$7:$Z$13,2) -> Research | F21: =RANDBETWEEN(1,7) -> 2 | G21: =VLOOKUP(F21,$AB$7:$AC$13,2) -> Senior Secondary | H21: =RANDBETWEEN(0,4) -> 1 | I21: =RANDBETWEEN(0,3) -> 3 | J21: =RANDBETWEEN(1,28) -> 25 | K21: =VLOOKUP(J21,$AE$7:$AF$34,2) -> Telangana | L21: =RANDBETWEEN(25000,99000) -> 84935 | M21: =L21*RANDBETWEEN(5,9) -> 594545 | N21: =RAND()*M21 -> 464004.44 | O21: =RAND()*I21*L21 -> 148200.33 | P21: =O21*RAND() -> 30145.594 | Q21: =RAND()*L21 -> 16438.474 | R21: =RAND()*L21 -> 27307.535 | S21: =M21+O21+R21 -> 770052.87 | T21: =N21+P21+Q21 -> 510588.51 | U21: =S21-T21 -> 259464.35 | AE21: 15 | AF21: Kerela
A22: =RANDBETWEEN(1,2) -> 2 | B22: =IF(A22=1,"M","F") -> F | C22: =RANDBETWEEN(1,7) -> 1 | D22: =RANDBETWEEN(18,45) -> 45 | E22: =VLOOKUP(C22,$Y$7:$Z$13,2) -> Engineering | F22: =RANDBETWEEN(1,7) -> 6 | G22: =VLOOKUP(F22,$AB$7:$AC$13,2) -> Doctorate | H22: =RANDBETWEEN(0,4) -> 4 | I22: =RANDBETWEEN(0,3) -> 3 | J22: =RANDBETWEEN(1,28) -> 27 | K22: =VLOOKUP(J22,$AE$7:$AF$34,2) -> Uttrakhand | L22: =RANDBETWEEN(25000,99000) -> 37034 | M22: =L22*RANDBETWEEN(5,9) -> 222204 | N22: =RAND()*M22 -> 71026.021 | O22: =RAND()*I22*L22 -> 48648.224 | P22: =O22*RAND() -> 1644.6774 | Q22: =RAND()*L22 -> 28388.192 | R22: =RAND()*L22 -> 34142.528 | S22: =M22+O22+R22 -> 304994.75 | T22: =N22+P22+Q22 -> 101058.89 | U22: =S22-T22 -> 203935.86 | AE22: 16 | AF22: Madhya Pradesh
A23: =RANDBETWEEN(1,2) -> 1 | B23: =IF(A23=1,"M","F") -> M | C23: =RANDBETWEEN(1,7) -> 6 | D23: =RANDBETWEEN(18,45) -> 20 | E23: =VLOOKUP(C23,$Y$7:$Z$13,2) -> Art | F23: =RANDBETWEEN(1,7) -> 1 | G23: =VLOOKUP(F23,$AB$7:$AC$13,2) -> Secondary | H23: =RANDBETWEEN(0,4) -> 3 | I23: =RANDBETWEEN(0,3) -> 3 | J23: =RANDBETWEEN(1,28) -> 27 | K23: =VLOOKUP(J23,$AE$7:$AF$34,2) -> Uttrakhand | L23: =RANDBETWEEN(25000,99000) -> 26604 | M23: =L23*RANDBETWEEN(5,9) -> 239436 | N23: =RAND()*M23 -> 65117.053 | O23: =RAND()*I23*L23 -> 42528.301 | P23: =O23*RAND() -> 21624.406 | Q23: =RAND()*L23 -> 26566.272 | R23: =RAND()*L23 -> 20756.042 | S23: =M23+O23+R23 -> 302720.34 | T23: =N23+P23+Q23 -> 113307.73 | U23: =S23-T23 -> 189412.61 | AE23: 17 | AF23: Manipur
A24: =RANDBETWEEN(1,2) -> 1 | B24: =IF(A24=1,"M","F") -> M | C24: =RANDBETWEEN(1,7) -> 4 | D24: =RANDBETWEEN(18,45) -> 44 | E24: =VLOOKUP(C24,$Y$7:$Z$13,2) -> Accounting | F24: =RANDBETWEEN(1,7) -> 3 | G24: =VLOOKUP(F24,$AB$7:$AC$13,2) -> UG | H24: =RANDBETWEEN(0,4) -> 3 | I24: =RANDBETWEEN(0,3) -> 2 | J24: =RANDBETWEEN(1,28) -> 20 | K24: =VLOOKUP(J24,$AE$7:$AF$34,2) -> Nagaland | L24: =RANDBETWEEN(25000,99000) -> 48133 | M24: =L24*RANDBETWEEN(5,9) -> 433197 | N24: =RAND()*M24 -> 258731.13 | O24: =RAND()*I24*L24 -> 2242.213 | P24: =O24*RAND() -> 371.70904 | Q24: =RAND()*L24 -> 3160.9457 | R24: =RAND()*L24 -> 1667.2344 | S24: =M24+O24+R24 -> 437106.45 | T24: =N24+P24+Q24 -> 262263.79 | U24: =S24-T24 -> 174842.66 | AE24: 18 | AF24: Meghalya
A25: =RANDBETWEEN(1,2) -> 1 | B25: =IF(A25=1,"M","F") -> M | C25: =RANDBETWEEN(1,7) -> 2 | D25: =RANDBETWEEN(18,45) -> 21 | E25: =VLOOKUP(C25,$Y$7:$Z$13,2) -> Healthcare | F25: =RANDBETWEEN(1,7) -> 3 | G25: =VLOOKUP(F25,$AB$7:$AC$13,2) -> UG | H25: =RANDBETWEEN(0,4) -> 3 | I25: =RANDBETWEEN(0,3) -> 2 | J25: =RANDBETWEEN(1,28) -> 8 | K25: =VLOOKUP(J25,$AE$7:$AF$34,2) -> Bihar | L25: =RANDBETWEEN(25000,99000) -> 35940 | M25: =L25*RANDBETWEEN(5,9) -> 215640 | N25: =RAND()*M25 -> 178811 | O25: =RAND()*I25*L25 -> 32669.837 | P25: =O25*RAND() -> 22117.22 | Q25: =RAND()*L25 -> 25917.324 | R25: =RAND()*L25 -> 2015.0004 | S25: =M25+O25+R25 -> 250324.84 | T25: =N25+P25+Q25 -> 226845.54 | U25: =S25-T25 -> 23479.297 | AE25: 19 | AF25: Mizoram
... A34: =RANDBETWEEN(1,2) -> 1 | B34: =IF(A34=1,"M","F") -> M | C34: =RANDBETWEEN(1,7) -> 3 | D34: =RANDBETWEEN(18,45) -> 45 | E34: =VLOOKUP(C34,$Y$7:$Z$13,2) -> IT | F34: =RANDBETWEEN(1,7) -> 1 | G34: =VLOOKUP(F34,$AB$7:$AC$13,2) -> Secondary | H34: =RANDBETWEEN(0,4) -> 3 | I34: =RANDBETWEEN(0,3) -> 3 | J34: =RANDBETWEEN(1,28) -> 18 | K34: =VLOOKUP(J34,$AE$7:$AF$34,2) -> Meghalya | L34: =RANDBETWEEN(25000,99000) -> 74385 | M34: =L34*RANDBETWEEN(5,9) -> 595080 | N34: =RAND()*M34 -> 246677.83 | O34: =RAND()*I34*L34 -> 127461.86 | P34: =O34*RAND() -> 46558.899 | Q34: =RAND()*L34 -> 8507.2429 | R34: =RAND()*L34 -> 18321.881 | S34: =M34+O34+R34 -> 740863.74 | T34: =N34+P34+Q34 -> 301743.97 | U34: =S34-T34 -> 439119.77 | AE34: 28 | AF34: West Bengal
A35: =RANDBETWEEN(1,2) -> 2 | B35: =IF(A35=1,"M","F") -> F | C35: =RANDBETWEEN(1,7) -> 6 | D35: =RANDBETWEEN(18,45) -> 19 | E35: =VLOOKUP(C35,$Y$7:$Z$13,2) -> Art | F35: =RANDBETWEEN(1,7) -> 4 | G35: =VLOOKUP(F35,$AB$7:$AC$13,2) -> PG | H35: =RANDBETWEEN(0,4) -> 3 | I35: =RANDBETWEEN(0,3) -> 3 | J35: =RANDBETWEEN(1,28) -> 16 | K35: =VLOOKUP(J35,$AE$7:$AF$34,2) -> Madhya Pradesh | L35: =RANDBETWEEN(25000,99000) -> 70958 | M35: =L35*RANDBETWEEN(5,9) -> 354790 | N35: =RAND()*M35 -> 217047.89 | O35: =RAND()*I35*L35 -> 164910.47 | P35: =O35*RAND() -> 111034.36 | Q35: =RAND()*L35 -> 70462.362 | R35: =RAND()*L35 -> 43641.558 | S35: =M35+O35+R35 -> 563342.03 | T35: =N35+P35+Q35 -> 398544.61 | U35: =S35-T35 -> 164797.43
A36: =RANDBETWEEN(1,2) -> 2 | B36: =IF(A36=1,"M","F") -> F | C36: =RANDBETWEEN(1,7) -> 1 | D36: =RANDBETWEEN(18,45) -> 19 | E36: =VLOOKUP(C36,$Y$7:$Z$13,2) -> Engineering | F36: =RANDBETWEEN(1,7) -> 6 | G36: =VLOOKUP(F36,$AB$7:$AC$13,2) -> Doctorate | H36: =RANDBETWEEN(0,4) -> 4 | I36: =RANDBETWEEN(0,3) -> 1 | J36: =RANDBETWEEN(1,28) -> 21 | K36: =VLOOKUP(J36,$AE$7:$AF$34,2) -> Odisha | L36: =RANDBETWEEN(25000,99000) -> 78407 | M36: =L36*RANDBETWEEN(5,9) -> 392035 | N36: =RAND()*M36 -> 134720.26 | O36: =RAND()*I36*L36 -> 75718.035 | P36: =O36*RAND() -> 64618.8 | Q36: =RAND()*L36 -> 5408.6843 | R36: =RAND()*L36 -> 37297.166 | S36: =M36+O36+R36 -> 505050.2 | T36: =N36+P36+Q36 -> 204747.75 | U36: =S36-T36 -> 300302.46
A37: =RANDBETWEEN(1,2) -> 1 | B37: =IF(A37=1,"M","F") -> M | C37: =RANDBETWEEN(1,7) -> 3 | D37: =RANDBETWEEN(18,45) -> 32 | E37: =VLOOKUP(C37,$Y$7:$Z$13,2) -> IT | F37: =RANDBETWEEN(1,7) -> 2 | G37: =VLOOKUP(F37,$AB$7:$AC$13,2) -> Senior Secondary | H37: =RANDBETWEEN(0,4) -> 2 | I37: =RANDBETWEEN(0,3) -> 0 | J37: =RANDBETWEEN(1,28) -> 1 | K37: =VLOOKUP(J37,$AE$7:$AF$34,2) -> Haryana | L37: =RANDBETWEEN(25000,99000) -> 38110 | M37: =L37*RANDBETWEEN(5,9) -> 304880 | N37: =RAND()*M37 -> 217782.72 | O37: =RAND()*I37*L37 -> 0 | P37: =O37*RAND() -> 0 | Q37: =RAND()*L37 -> 5375.0794 | R37: =RAND()*L37 -> 29275.484 | S37: =M37+O37+R37 -> 334155.48 | T37: =N37+P37+Q37 -> 223157.8 | U37: =S37-T37 -> 110997.68
A38: =RANDBETWEEN(1,2) -> 1 | B38: =IF(A38=1,"M","F") -> M | C38: =RANDBETWEEN(1,7) -> 6 | D38: =RANDBETWEEN(18,45) -> 40 | E38: =VLOOKUP(C38,$Y$7:$Z$13,2) -> Art | F38: =RANDBETWEEN(1,7) -> 6 | G38: =VLOOKUP(F38,$AB$7:$AC$13,2) -> Doctorate | H38: =RANDBETWEEN(0,4) -> 0 | I38: =RANDBETWEEN(0,3) -> 2 | J38: =RANDBETWEEN(1,28) -> 14 | K38: =VLOOKUP(J38,$AE$7:$AF$34,2) -> Karnataka | L38: =RANDBETWEEN(25000,99000) -> 38339 | M38: =L38*RANDBETWEEN(5,9) -> 268373 | N38: =RAND()*M38 -> 260616.75 | O38: =RAND()*I38*L38 -> 22158.071 | P38: =O38*RAND() -> 5568.4182 | Q38: =RAND()*L38 -> 3406.6358 | R38: =RAND()*L38 -> 19221.248 | S38: =M38+O38+R38 -> 309752.32 | T38: =N38+P38+Q38 -> 269591.8 | U38: =S38-T38 -> 40160.519
A39: =RANDBETWEEN(1,2) -> 1 | B39: =IF(A39=1,"M","F") -> M | C39: =RANDBETWEEN(1,7) -> 5 | D39: =RANDBETWEEN(18,45) -> 38 | E39: =VLOOKUP(C39,$Y$7:$Z$13,2) -> Research | F39: =RANDBETWEEN(1,7) -> 5 | G39: =VLOOKUP(F39,$AB$7:$AC$13,2) -> Diploma | H39: =RANDBETWEEN(0,4) -> 1 | I39: =RANDBETWEEN(0,3) -> 1 | J39: =RANDBETWEEN(1,28) -> 24 | K39: =VLOOKUP(J39,$AE$7:$AF$34,2) -> Tamil Nadu | L39: =RANDBETWEEN(25000,99000) -> 25703 | M39: =L39*RANDBETWEEN(5,9) -> 179921 | N39: =RAND()*M39 -> 72135.427 | O39: =RAND()*I39*L39 -> 14844.183 | P39: =O39*RAND() -> 4437.2281 | Q39: =RAND()*L39 -> 7934.1809 | R39: =RAND()*L39 -> 24098.841 | S39: =M39+O39+R39 -> 218864.02 | T39: =N39+P39+Q39 -> 84506.836 | U39: =S39-T39 -> 134357.19
A40: =RANDBETWEEN(1,2) -> 1 | B40: =IF(A40=1,"M","F") -> M | C40: =RANDBETWEEN(1,7) -> 3 | D40: =RANDBETWEEN(18,45) -> 28 | E40: =VLOOKUP(C40,$Y$7:$Z$13,2) -> IT | F40: =RANDBETWEEN(1,7) -> 2 | G40: =VLOOKUP(F40,$AB$7:$AC$13,2) -> Senior Secondary | H40: =RANDBETWEEN(0,4) -> 4 | I40: =RANDBETWEEN(0,3) -> 1 | J40: =RANDBETWEEN(1,28) -> 11 | K40: =VLOOKUP(J40,$AE$7:$AF$34,2) -> Goa | L40: =RANDBETWEEN(25000,99000) -> 42562 | M40: =L40*RANDBETWEEN(5,9) -> 340496 | N40: =RAND()*M40 -> 174839.15 | O40: =RAND()*I40*L40 -> 17659.024 | P40: =O40*RAND() -> 11613.225 | Q40: =RAND()*L40 -> 15861.759 | R40: =RAND()*L40 -> 41108.908 | S40: =M40+O40+R40 -> 399263.93 | T40: =N40+P40+Q40 -> 202314.13 | U40: =S40-T40 -> 196949.8
A41: =RANDBETWEEN(1,2) -> 2 | B41: =IF(A41=1,"M","F") -> F | C41: =RANDBETWEEN(1,7) -> 3 | D41: =RANDBETWEEN(18,45) -> 39 | E41: =VLOOKUP(C41,$Y$7:$Z$13,2) -> IT | F41: =RANDBETWEEN(1,7) -> 3 | G41: =VLOOKUP(F41,$AB$7:$AC$13,2) -> UG | H41: =RANDBETWEEN(0,4) -> 0 | I41: =RANDBETWEEN(0,3) -> 0 | J41: =RANDBETWEEN(1,28) -> 27 | K41: =VLOOKUP(J41,$AE$7:$AF$34,2) -> Uttrakhand | L41: =RANDBETWEEN(25000,99000) -> 88182 | M41: =L41*RANDBETWEEN(5,9) -> 617274 | N41: =RAND()*M41 -> 10408.751 | O41: =RAND()*I41*L41 -> 0 | P41: =O41*RAND() -> 0 | Q41: =RAND()*L41 -> 38965.694 | R41: =RAND()*L41 -> 81486.789 | S41: =M41+O41+R41 -> 698760.79 | T41: =N41+P41+Q41 -> 49374.445 | U41: =S41-T41 -> 649386.34
A42: =RANDBETWEEN(1,2) -> 1 | B42: =IF(A42=1,"M","F") -> M | C42: =RANDBETWEEN(1,7) -> 4 | D42: =RANDBETWEEN(18,45) -> 25 | E42: =VLOOKUP(C42,$Y$7:$Z$13,2) -> Accounting | F42: =RANDBETWEEN(1,7) -> 3 | G42: =VLOOKUP(F42,$AB$7:$AC$13,2) -> UG | H42: =RANDBETWEEN(0,4) -> 3 | I42: =RANDBETWEEN(0,3) -> 2 | J42: =RANDBETWEEN(1,28) -> 16 | K42: =VLOOKUP(J42,$AE$7:$AF$34,2) -> Madhya Pradesh | L42: =RANDBETWEEN(25000,99000) -> 78359 | M42: =L42*RANDBETWEEN(5,9) -> 391795 | N42: =RAND()*M42 -> 108491.5 | O42: =RAND()*I42*L42 -> 46424.155 | P42: =O42*RAND() -> 14357.03 | Q42: =RAND()*L42 -> 8437.6677 | R42: =RAND()*L42 -> 52824.211 | S42: =M42+O42+R42 -> 491043.37 | T42: =N42+P42+Q42 -> 131286.19 | U42: =S42-T42 -> 359757.17
A43: =RANDBETWEEN(1,2) -> 1 | B43: =IF(A43=1,"M","F") -> M | C43: =RANDBETWEEN(1,7) -> 3 | D43: =RANDBETWEEN(18,45) -> 33 | E43: =VLOOKUP(C43,$Y$7:$Z$13,2) -> IT | F43: =RANDBETWEEN(1,7) -> 2 | G43: =VLOOKUP(F43,$AB$7:$AC$13,2) -> Senior Secondary | H43: =RANDBETWEEN(0,4) -> 1 | I43: =RANDBETWEEN(0,3) -> 2 | J43: =RANDBETWEEN(1,28) -> 16 | K43: =VLOOKUP(J43,$AE$7:$AF$34,2) -> Madhya Pradesh | L43: =RANDBETWEEN(25000,99000) -> 25579 | M43: =L43*RANDBETWEEN(5,9) -> 204632 | N43: =RAND()*M43 -> 103743.84 | O43: =RAND()*I43*L43 -> 44705.223 | P43: =O43*RAND() -> 15703.347 | Q43: =RAND()*L43 -> 7226.3976 | R43: =RAND()*L43 -> 12412.987 | S43: =M43+O43+R43 -> 261750.21 | T43: =N43+P43+Q43 -> 126673.58 | U43: =S43-T43 -> 135076.63
A44: =RANDBETWEEN(1,2) -> 2 | B44: =IF(A44=1,"M","F") -> F | C44: =RANDBETWEEN(1,7) -> 5 | D44: =RANDBETWEEN(18,45) -> 36 | E44: =VLOOKUP(C44,$Y$7:$Z$13,2) -> Research | F44: =RANDBETWEEN(1,7) -> 5 | G44: =VLOOKUP(F44,$AB$7:$AC$13,2) -> Diploma | H44: =RANDBETWEEN(0,4) -> 1 | I44: =RANDBETWEEN(0,3) -> 3 | J44: =RANDBETWEEN(1,28) -> 26 | K44: =VLOOKUP(J44,$AE$7:$AF$34,2) -> Tripura | L44: =RANDBETWEEN(25000,99000) -> 31740 | M44: =L44*RANDBETWEEN(5,9) -> 253920 | N44: =RAND()*M44 -> 86232.446 | O44: =RAND()*I44*L44 -> 58341.555 | P44: =O44*RAND() -> 16238.435 | Q44: =RAND()*L44 -> 17340.662 | R44: =RAND()*L44 -> 4036.7415 | S44: =M44+O44+R44 -> 316298.3 | T44: =N44+P44+Q44 -> 119811.54 | U44: =S44-T44 -> 196486.75
A45: =RANDBETWEEN(1,2) -> 2 | B45: =IF(A45=1,"M","F") -> F | C45: =RANDBETWEEN(1,7) -> 5 | D45: =RANDBETWEEN(18,45) -> 38 | E45: =VLOOKUP(C45,$Y$7:$Z$13,2) -> Research | F45: =RANDBETWEEN(1,7) -> 5 | G45: =VLOOKUP(F45,$AB$7:$AC$13,2) -> Diploma | H45: =RANDBETWEEN(0,4) -> 4 | I45: =RANDBETWEEN(0,3) -> 2 | J45: =RANDBETWEEN(1,28) -> 14 | K45: =VLOOKUP(J45,$AE$7:$AF$34,2) -> Karnataka | L45: =RANDBETWEEN(25000,99000) -> 46336 | M45: =L45*RANDBETWEEN(5,9) -> 278016 | N45: =RAND()*M45 -> 57904.374 | O45: =RAND()*I45*L45 -> 62238.4 | P45: =O45*RAND() -> 17618.624 | Q45: =RAND()*L45 -> 35853.807 | R45: =RAND()*L45 -> 365.23926 | S45: =M45+O45+R45 -> 340619.64 | T45: =N45+P45+Q45 -> 111376.8 | U45: =S45-T45 -> 229242.84
A46: =RANDBETWEEN(1,2) -> 2 | B46: =IF(A46=1,"M","F") -> F | C46: =RANDBETWEEN(1,7) -> 2 | D46: =RANDBETWEEN(18,45) -> 28 | E46: =VLOOKUP(C46,$Y$7:$Z$13,2) -> Healthcare | F46: =RANDBETWEEN(1,7) -> 6 | G46: =VLOOKUP(F46,$AB$7:$AC$13,2) -> Doctorate | H46: =RANDBETWEEN(0,4) -> 2 | I46: =RANDBETWEEN(0,3) -> 0 | J46: =RANDBETWEEN(1,28) -> 18 | K46: =VLOOKUP(J46,$AE$7:$AF$34,2) -> Meghalya | L46: =RANDBETWEEN(25000,99000) -> 42681 | M46: =L46*RANDBETWEEN(5,9) -> 256086 | N46: =RAND()*M46 -> 143759.7 | O46: =RAND()*I46*L46 -> 0 | P46: =O46*RAND() -> 0 | Q46: =RAND()*L46 -> 38537.555 | R46: =RAND()*L46 -> 39109.137 | S46: =M46+O46+R46 -> 295195.14 | T46: =N46+P46+Q46 -> 182297.25 | U46: =S46-T46 -> 112897.88
... A507: =RANDBETWEEN(1,2) -> 1 | B507: =IF(A507=1,"M","F") -> M | C507: =RANDBETWEEN(1,7) -> 7 | D507: =RANDBETWEEN(18,45) -> 34 | E507: =VLOOKUP(C507,$Y$7:$Z$13,2) -> Other | F507: =RANDBETWEEN(1,7) -> 7 | G507: =VLOOKUP(F507,$AB$7:$AC$13,2) -> Other | H507: =RANDBETWEEN(0,4) -> 1 | I507: =RANDBETWEEN(0,3) -> 1 | J507: =RANDBETWEEN(1,28) -> 17 | K507: =VLOOKUP(J507,$AE$7:$AF$34,2) -> Manipur | L507: =RANDBETWEEN(25000,99000) -> 35170 | M507: =L507*RANDBETWEEN(5,9) -> 211020 | N507: =RAND()*M507 -> 33251.857 | O507: =RAND()*I507*L507 -> 15163.562 | P507: =O507*RAND() -> 14211.41 | Q507: =RAND()*L507 -> 11638.671 | R507: =RAND()*L507 -> 2154.2297 | S507: =M507+O507+R507 -> 228337.79 | T507: =N507+P507+Q507 -> 59101.938 | U507: =S507-T507 -> 169235.85

Sheet Dashboard
N2: Basic Data Extraction
B5: Number of Men vs. Number of Women | E5: Average Age | H5: Number of People by Profession | P5: Average Income | S5: Average Value of 1 Car | V5: Number of People with debts > 1,00,000 | AA5: Number of people with Mortgage left > 1,00,000
B6: Number of M | C6: Number of F | E6: =AVERAGE(Population_Data!D7:D507) -> 31.502994 | H6: Engineering | I6: Healthcare | J6: IT | K6: Accounting | L6: Research | M6: Art | N6: Other | P6: =AVERAGE(Population_Data!B7:AC507) -> 117388.8 | S6: =T8/S8 -> 31423.185 | V6: =COUNTIF(Population_Data!T7:T507,">100000") -> 431 | AA6: =COUNTIF(Population_Data!N7:N507,">100000") -> 377
B7: =COUNTIF(Table1[Gender],"M") -> 242 | C7: =COUNTIF(Population_Data!B7:B507,"F") -> 259 | E7: Average age of M | F7: Average age of F | H7: =COUNTIF(Population_Data!E7:E507,Dashboard!H6) -> 62 | I7: =COUNTIF(Population_Data!E7:E507,Dashboard!I6) -> 75 | J7: =COUNTIF(Population_Data!E7:E507,Dashboard!J6) -> 80 | K7: =COUNTIF(Population_Data!E7:E507,Dashboard!K6) -> 68 | L7: =COUNTIF(Population_Data!E7:E507,Dashboard!L6) -> 82 | M7: =COUNTIF(Population_Data!E7:E507,Dashboard!M6) -> 62 | N7: =COUNTIF(Population_Data!E7:E507,Dashboard!N6) -> 72 | P7: Average Income of M | Q7: Average Income of F | S7: Total cars | T7: Total Value of all cars
E8: =AVERAGEIF(Population_Data!B7:B507,"M",Population_Data!D7:D507) -> 31.380165 | F8: =AVERAGEIF(Population_Data!B7:B507,"F",Population_Data!D7:D507) -> 31.617761 | P8: =AVERAGEIF(Population_Data!B7:B507,"M",Population_Data!L7:L507) -> 63383.872 | Q8: =AVERAGEIF(Population_Data!B7:B507,"F",Population_Data!L7:L507) -> 63571.29 | S8: =SUM(Population_Data!I7:I507) -> 725 | T8: =SUM(Population_Data!O7:O507) -> 22781809
B20: Number of People by Area
B21: Haryana | C21: Uttar Pradesh | D21: Punjab | E21: Maharashtra | F21: Andhra Pradesh | G21: Arunachal Pradesh | H21: Assam | I21: Bihar | J21: Chhattisgarh | K21: Gujarat | L21: Goa | M21: Himachal Pradesh | N21: Jharkhand | O21: Karnataka | P21: Kerela | Q21: Madhya Pradesh | R21: Manipur | S21: Meghalya | T21: Mizoram | U21: Nagaland | V21: Odisha | W21: Rajasthan | X21: Sikkim | Y21: Tamil Nadu | Z21: Telangana | AA21: Tripura | AB21: Uttrakhand | AC21: West Bengal
B22: =COUNTIF(Population_Data!$K$7:$K$507,Dashboard!B21) -> 15 | C22: =COUNTIF(Population_Data!$K$7:$K$507,Dashboard!C21) -> 17 | D22: =COUNTIF(Population_Data!$K$7:$K$507,Dashboard!D21) -> 16 | E22: =COUNTIF(Population_Data!$K$7:$K$507,Dashboard!E21) -> 13 | F22: =COUNTIF(Population_Data!$K$7:$K$507,Dashboard!F21) -> 18 | G22: =COUNTIF(Population_Data!$K$7:$K$507,Dashboard!G21) -> 12 | H22: =COUNTIF(Population_Data!$K$7:$K$507,Dashboard!H21) -> 18 | I22: =COUNTIF(Population_Data!$K$7:$K$507,Dashboard!I21) -> 15 | ... AC22: =COUNTIF(Population_Data!$K$7:$K$507,Dashboard!AC21) -> 18
N43: Advanced Data Extraction
B46: Total Income By Area
B47: Haryana | C47: Uttar Pradesh | D47: Punjab | E47: Maharashtra | F47: Andhra Pradesh | G47: Arunachal Pradesh | H47: Assam | I47: Bihar | J47: Chhattisgarh | K47: Gujarat | L47: Goa | M47: Himachal Pradesh | N47: Jharkhand | O47: Karnataka | P47: Kerela | Q47: Madhya Pradesh | R47: Manipur | S47: Meghalya | T47: Mizoram | U47: Nagaland | V47: Odisha | W47: Rajasthan | X47: Sikkim | Y47: Tamil Nadu | Z47: Telangana | AA47: Tripura | AB47: Uttrakhand | AC47: West Bengal
B48: =SUMIF(Population_Data!$K$7:$K$507,Dashboard!B47,Population_Data!$L$7:$L$507) -> 878514 | C48: =SUMIF(Population_Data!$K$7:$K$507,Dashboard!C47,Population_Data!$L$7:$L$507) -> 1177880 | D48: =SUMIF(Population_Data!$K$7:$K$507,Dashboard!D47,Population_Data!$L$7:$L$507) -> 1003081 | E48: =SUMIF(Population_Data!$K$7:$K$507,Dashboard!E47,Population_Data!$L$7:$L$507) -> 851535 | F48: =SUMIF(Population_Data!$K$7:$K$507,Dashboard!F47,Population_Data!$L$7:$L$507) -> 1059950 | G48: =SUMIF(Population_Data!$K$7:$K$507,Dashboard!G47,Population_Data!$L$7:$L$507) -> 681262 | H48: =SUMIF(Population_Data!$K$7:$K$507,Dashboard!H47,Population_Data!$L$7:$L$507) -> 1175535 | I48: =SUMIF(Population_Data!$K$7:$K$507,Dashboard!I47,Population_Data!$L$7:$L$507) -> 934195 | ... AC48: =SUMIF(Population_Data!$K$7:$K$507,Dashboard!AC47,Population_Data!$L$7:$L$507) -> 1225795
B50: Average Income by Area
B51: Haryana | C51: Uttar Pradesh | D51: Punjab | E51: Maharashtra | F51: Andhra Pradesh | G51: Arunachal Pradesh | H51: Assam | I51: Bihar | J51: Chhattisgarh | K51: Gujarat | L51: Goa | M51: Himachal Pradesh | N51: Jharkhand | O51: Karnataka | P51: Kerela | Q51: Madhya Pradesh | R51: Manipur | S51: Meghalya | T51: Mizoram | U51: Nagaland | V51: Odisha | W51: Rajasthan | X51: Sikkim | Y51: Tamil Nadu | Z51: Telangana | AA51: Tripura | AB51: Uttrakhand | AC51: West Bengal
B52: =B48/B22 -> 58567.6 | C52: =C48/C22 -> 69287.059 | D52: =D48/D22 -> 62692.562 | E52: =E48/E22 -> 65502.692 | F52: =F48/F22 -> 58886.111 | G52: =G48/G22 -> 56771.833 | H52: =H48/H22 -> 65307.5 | I52: =I48/I22 -> 62279.667 | ... AC52: =AC48/AC22 -> 68099.722
B69: Total Income by Profession | J69: Average age of people having Networth > 1,00,000
B70: Engineering | C70: Healthcare | D70: IT | E70: Accounting | F70: Research | G70: Art | H70: Other | K70: =AVERAGEIF(Table1[Net Worth],"> 100000",Table1[Age]) -> 31.439153
B71: =SUMIF(Population_Data!$E$7:$E$507,Dashboard!B70,Population_Data!$L$7:$L$507) -> 3983817 | C71: =SUMIF(Population_Data!$E$7:$E$507,Dashboard!C70,Population_Data!$L$7:$L$507) -> 4541927 | D71: =SUMIF(Population_Data!$E$7:$E$507,Dashboard!D70,Population_Data!$L$7:$L$507) -> 4969154 | E71: =SUMIF(Population_Data!$E$7:$E$507,Dashboard!E70,Population_Data!$L$7:$L$507) -> 4546196 | F71: =SUMIF(Population_Data!$E$7:$E$507,Dashboard!F70,Population_Data!$L$7:$L$507) -> 5100498 | G71: =SUMIF(Population_Data!$E$7:$E$507,Dashboard!G70,Population_Data!$L$7:$L$507) -> 4067163 | H71: =SUMIF(Population_Data!$E$7:$E$507,Dashboard!H70,Population_Data!$L$7:$L$507) -> 4595106
B73: Average Income by Profession | J73: Number of People having Liabilities more than income
B74: Engineering | C74: Healthcare | D74: IT | E74: Accounting | F74: Research | G74: Art | H74: Other | K74: {=SUMPRODUCT(--(Population_Data!T2:T507>Population_Data!L2:L507))} -> 486
B75: =B71/H7 -> 64255.113 | C75: =C71/I7 -> 60559.027 | D75: =D71/J7 -> 62114.425 | E75: =E71/K7 -> 66855.824 | F75: =F71/L7 -> 62201.195 | G75: =G71/M7 -> 65599.403 | H75: =H71/N7 -> 63820.917
